allotropy/__about__.py
allotropy/__init__.py
allotropy/constants.py
allotropy/exceptions.py
allotropy/named_file_contents.py
allotropy/parser_factory.py
allotropy/py.typed
allotropy/to_allotrope.py
allotropy/to_dataset.py
allotropy/types.py
allotropy/allotrope/__init__.py
allotropy/allotrope/allotrope.py
allotropy/allotrope/converter.py
allotropy/allotrope/schemas.py
allotropy/allotrope/models/__init__.py
allotropy/allotrope/models/adm/__init__.py
allotropy/allotrope/models/adm/binding_affinity/__init__.py
allotropy/allotrope/models/adm/binding_affinity/rec/__init__.py
allotropy/allotrope/models/adm/binding_affinity/rec/_2025/__init__.py
allotropy/allotrope/models/adm/binding_affinity/rec/_2025/_03/__init__.py
allotropy/allotrope/models/adm/binding_affinity/rec/_2025/_03/binding_affinity.py
allotropy/allotrope/models/adm/binding_affinity_analyzer/__init__.py
allotropy/allotrope/models/adm/binding_affinity_analyzer/wd/__init__.py
allotropy/allotrope/models/adm/binding_affinity_analyzer/wd/_2024/__init__.py
allotropy/allotrope/models/adm/binding_affinity_analyzer/wd/_2024/_12/__init__.py
allotropy/allotrope/models/adm/binding_affinity_analyzer/wd/_2024/_12/binding_affinity_analyzer.py
allotropy/allotrope/models/adm/cell_counting/__init__.py
allotropy/allotrope/models/adm/cell_counting/benchling/__init__.py
allotropy/allotrope/models/adm/cell_counting/benchling/_2023/__init__.py
allotropy/allotrope/models/adm/cell_counting/benchling/_2023/_09/__init__.py
allotropy/allotrope/models/adm/cell_counting/benchling/_2023/_09/cell_counting.py
allotropy/allotrope/models/adm/cell_counting/benchling/_2023/_11/__init__.py
allotropy/allotrope/models/adm/cell_counting/benchling/_2023/_11/cell_counting.py
allotropy/allotrope/models/adm/cell_counting/rec/__init__.py
allotropy/allotrope/models/adm/cell_counting/rec/_2024/__init__.py
allotropy/allotrope/models/adm/cell_counting/rec/_2024/_09/__init__.py
allotropy/allotrope/models/adm/cell_counting/rec/_2024/_09/cell_counting.py
allotropy-0.1.112.dist-info/METADATA
allotropy-0.1.112.dist-info/WHEEL
allotropy-0.1.112.dist-info/licenses/LICENSE.txt
allotropy-0.1.112.dist-info/RECORD
