Metadata-Version: 2.4
Name: allotropy
Version: 0.1.112
Summary: Converts to ASM (Allotrope Simple Model) from various file formats.
Project-URL: Documentation, https://github.com/Benchling-Open-Source/allotropy#readme
Project-URL: Issues, https://github.com/Benchling-Open-Source/allotropy/issues
Project-URL: Source, https://github.com/Benchling-Open-Source/allotropy
Author-email: Benchling Open Source <opensource@benchling.com>, Lukas Boelling <lukas.boelling@deepgenomics.com>, Oscar Castro <oscar.castro@benchling.com>, Nick Collins <nick.collins@benchling.com>, Danielle Chou <danielle.chou@benchling.com>, Jane Dance <jane.dance@abcellera.com>, Chris Friedline <chris.friedline@benchling.com>, Kathy Garcia <kathy@benchling.com>, Trevor Halum <trevor.halum@deepgenomics.com>, Joshua Hernandez <jherna@benchling.com>, Sebastian Lopez <sebastian.cardona@benchling
License-File: LICENSE.txt
Keywords: allotrope,allotropy,asm,benchling,converters
Classifier: Development Status :: 4 - Beta
Classifier: License :: OSI Approved :: MIT License
Classifier: Programming Language :: Python
Classifier: Programming Language :: Python :: 3.10
Classifier: Programming Language :: Python :: 3.11
Classifier: Typing :: Typed
Requires-Python: >=3.10
Requires-Dist: cattrs>=23.2.0
Requires-Dist: chardet>=5.2.0
Requires-Dist: defusedxml>=0.7.1
Requires-Dist: jsonschema<4.18.0,>=4.3.3
Requires-Dist: numpy>=1.25.0
Requires-Dist: olefile>=0.47
Requires-Dist: openpyxl>=3.1.0
Requires-Dist: pandas>=2.2.0
Requires-Dist: python-calamine>=0.2.3
Requires-Dist: rainbow-api==1.0.10
Requires-Dist: rfc3339-validator>=0.1.4
Requires-Dist: types-defusedxml>=0.7.0.20240218
Requires-Dist: xlrd>=2.0.0
Requires-Dist: xmltodict>=0.13.0
